intake_dynamodb/__init__.py
intake_dynamodb/dynamodb.py
intake_dynamodb-2023.5.0.dist-info/LICENSE
intake_dynamodb-2023.5.0.dist-info/METADATA
intake_dynamodb-2023.5.0.dist-info/WHEEL
intake_dynamodb-2023.5.0.dist-info/entry_points.txt
intake_dynamodb-2023.5.0.dist-info/top_level.txt
intake_dynamodb-2023.5.0.dist-info/RECORD
