Metadata-Version: 2.1
Name: intake-dynamodb
Version: 2023.5.0
Summary: Intake plugin for reading data from dynamodb
Author-email: Ray Bell <rayjohnbell0@gmail.com>
Project-URL: repository, https://github.com/intake-dynamodb/intake-dynamodb
License-File: LICENSE
Requires-Dist: dask[dataframe]
Requires-Dist: intake
Requires-Dist: s3fs
Provides-Extra: dev
Requires-Dist: black ; extra == 'dev'
Requires-Dist: moto[dynamodb,s3] ; extra == 'dev'
Requires-Dist: mypy ; extra == 'dev'
Requires-Dist: pre-commit ; extra == 'dev'
Requires-Dist: pytest ; extra == 'dev'
Requires-Dist: ruff ; extra == 'dev'
Requires-Dist: yamllint ; extra == 'dev'
